cua_som-0.1.3.dist-info/METADATA
cua_som-0.1.3.dist-info/WHEEL
cua_som-0.1.3.dist-info/entry_points.txt
som/__init__.py
som/detect.py
som/detection.py
som/models.py
som/ocr.py
som/util/utils.py
som/visualization.py
cua_som-0.1.3.dist-info/RECORD
