Metadata-Version: 2.1
Name: cua-som
Version: 0.1.3
Summary: Computer Vision and OCR library for detecting and analyzing UI elements
Keywords: computer-vision,ocr,ui-analysis,icon-detection
Author-Email: TryCua <gh@trycua.com>
License: MIT
Classifier: Development Status :: 4 - Beta
Classifier: Intended Audience :: Developers
Classifier: License :: OSI Approved :: MIT License
Classifier: Programming Language :: Python :: 3
Classifier: Programming Language :: Python :: 3.11
Classifier: Topic :: Scientific/Engineering :: Artificial Intelligence
Classifier: Topic :: Scientific/Engineering :: Image Recognition
Project-URL: Homepage, https://github.com/trycua/cua
Project-URL: Repository, https://github.com/trycua/cua
Project-URL: Documentation, https://github.com/trycua/cua/tree/main/docs
Requires-Python: >=3.10
Requires-Dist: torch>=2.2.1
Requires-Dist: torchvision>=0.17.1
Requires-Dist: ultralytics>=8.1.28
Requires-Dist: easyocr>=1.7.1
Requires-Dist: numpy>=1.26.4
Requires-Dist: pillow>=10.2.0
Requires-Dist: setuptools>=75.8.1
Requires-Dist: opencv-python-headless>=4.11.0.86
Requires-Dist: matplotlib>=3.8.3
Requires-Dist: huggingface-hub>=0.21.4
Requires-Dist: supervision>=0.25.1
Requires-Dist: typing-extensions>=4.9.0
Requires-Dist: pydantic>=2.6.3
